ameide_sdk/__init__.py
ameide_sdk/client.py
ameide_sdk/config.py
ameide_sdk/errors.py
ameide_sdk/interceptors.py
ameide_sdk/retry.py
buf/validate/__init__.py
buf/validate/validate_pb2.py
ameide_sdk-0.1.0.dist-info/METADATA
ameide_sdk-0.1.0.dist-info/WHEEL
ameide_sdk-0.1.0.dist-info/top_level.txt
ameide_sdk-0.1.0.dist-info/RECORD
