Metadata-Version: 2.4
Name: ameide-sdk
Version: 0.1.0
Summary: Official AMEIDE Python SDK
Author: AMEIDE Team
Author-email: team@ameide.io
Requires-Python: >=3.12
Requires-Dist: grpcio>=1.65.5
Requires-Dist: protobuf>=5.28.0
Dynamic: author
Dynamic: author-email
Dynamic: requires-dist
Dynamic: requires-python
Dynamic: summary
